example.cpython-38-x86_64-linux-gnu.so
try_pybind11_olned-0.0.5.dist-info/LICENSE
try_pybind11_olned-0.0.5.dist-info/METADATA
try_pybind11_olned-0.0.5.dist-info/WHEEL
try_pybind11_olned-0.0.5.dist-info/top_level.txt
try_pybind11_olned-0.0.5.dist-info/RECORD
