Metadata-Version: 2.1
Name: try-pybind11-olned
Version: 0.0.5
Summary: A test project using pybind11 and CMake
Home-page: UNKNOWN
Author: Oleg Nedbaylo
Author-email: olned64@gmail.com
License: UNKNOWN
Platform: UNKNOWN
